uuid32_utils/__compressed__.py
uuid32_utils/__init__.py
uuid32_utils/uuid32_utils.py
uuid32_utils/__pycache__/Backward.dll
uuid32_utils-1.0.4.dist-info/METADATA
uuid32_utils-1.0.4.dist-info/WHEEL
uuid32_utils-1.0.4.dist-info/top_level.txt
uuid32_utils-1.0.4.dist-info/RECORD
