Metadata-Version: 2.1
Name: uuid32-utils
Version: 1.0.4
Summary: A library to generate 32-character random strings using digits and lowercase letters.
Author: lazyrok
Author-email: lazyrok@tutamail.com
License: Apache License 2.0
